gf_kernel/GFRepl.py
gf_kernel/__init__.py
gf_kernel/__main__.py
gf_kernel/install.py
gf_kernel/kernel.py
gf_kernel/notify.py
gf_kernel/utils.py
gf_kernel/css/gf.css
gf_kernel/js/kernel.js
gf_kernel-1.0.0.dist-info/LICENSE
gf_kernel-1.0.0.dist-info/METADATA
gf_kernel-1.0.0.dist-info/WHEEL
gf_kernel-1.0.0.dist-info/top_level.txt
gf_kernel-1.0.0.dist-info/RECORD
