Metadata-Version: 2.1
Name: gf-kernel
Version: 1.0.0
Summary: Simple example kernel for GF
Home-page: https://github.com/UniFormal/gf_kernel
Author: Kai Amann
Author-email: kai.amann@fau.de
License: UNKNOWN
Platform: UNKNOWN
Classifier: Intended Audience :: Developers
Classifier: License :: OSI Approved :: GNU General Public License v3 (GPLv3)
Classifier: Programming Language :: Python :: 3
Requires-Dist: ipykernel (>=5.1.0)
Requires-Dist: ipython (>=7.2.0)
Requires-Dist: ipywidgets (>=7.4.2)
Requires-Dist: jupyter (>=1.0.0)
Requires-Dist: jupyter-client (>=5.2.4)
